nbkickoff/__about__.py
nbkickoff/__init__.py
nbkickoff/__main__.py
nbkickoff/nbkickoff.py
nbkickoff/template.py
nbkickoff-0.1.0.dist-info/LICENSE.txt
nbkickoff-0.1.0.dist-info/METADATA
nbkickoff-0.1.0.dist-info/RECORD
nbkickoff-0.1.0.dist-info/WHEEL
nbkickoff-0.1.0.dist-info/entry_points.txt
nbkickoff-0.1.0.dist-info/top_level.txt
