Metadata-Version: 2.1
Name: nbkickoff
Version: 0.1.0
Summary: Launch an IPython Notebook from a template notebook file
Home-page: https://github.com/lumicks/nbkickoff
Author: Lumicks B.V.
Author-email: devteam@lumicks.com
License: Apache License 2.0
Platform: UNKNOWN
Classifier: Development Status :: 3 - Alpha
Classifier: Framework :: Jupyter
Classifier: License :: OSI Approved :: Apache Software License
Classifier: Operating System :: OS Independent
Classifier: Programming Language :: Python :: 3 :: Only
Classifier: Programming Language :: Python :: 3.6
Classifier: Topic :: Scientific/Engineering
Requires-Python: >=3
Requires-Dist: notebook (>=5.5.0)
Requires-Dist: nbformat (>=4.4)
